[
  {
    "skillId": 1,
    "skillName": "Beginner Guitar Lessons",
    "providerName": "Alex Martin",
    "providerEmail": "alex@skillswap.com",
    "price": 20,
    "rating": 4.8,
    "slotsAvailable": 3,
    "description": "Acoustic guitar classes for complete beginners.",
    "image": "https://i.postimg.cc/j2j3cN7q/guitar-lessons.png",
    "category": "Music"
  },
  {
    "skillId": 2,
    "skillName": "Spoken English Practice",
    "providerName": "Sara Hossain",
    "providerEmail": "sara@skillswap.com",
    "price": 10,
    "rating": 4.6,
    "slotsAvailable": 5,
    "description": "Conversational English sessions for non-native speakers.",
    "image": "https://i.postimg.cc/59pWcQff/spoken-english.png",
    "category": "Language"
  },
  {
    "skillId": 3,
    "skillName": "UI/UX Design Fundamentals",
    "providerName": "Daniel Lee",
    "providerEmail": "daniel@skillswap.com",
    "price": 35,
    "rating": 4.9,
    "slotsAvailable": 4,
    "description": "Learn user interface and experience design with Figma and Adobe XD.",
    "image": "https://i.postimg.cc/vBsrCMfL/ui-ux-design.png",
    "category": "Design"
  },
  {
    "skillId": 4,
    "skillName": "Basic Photography Course",
    "providerName": "Linda Roy",
    "providerEmail": "linda@skillswap.com",
    "price": 18,
    "rating": 4.5,
    "slotsAvailable": 6,
    "description": "Master lighting, framing, and editing for stunning photos.",
    "image": "https://i.postimg.cc/MGXYxyTY/photography.png",
    "category": "Photography"
  },
  {
    "skillId": 5,
    "skillName": "Web Development Bootcamp",
    "providerName": "Kevin Patel",
    "providerEmail": "kevin@skillswap.com",
    "price": 45,
    "rating": 4.9,
    "slotsAvailable": 2,
    "description": "A complete course on HTML, CSS, JavaScript, and React.",
    "image": "https://i.postimg.cc/yx8V7kYq/web-dev.png",
    "category": "Technology"
  },
  {
    "skillId": 6,
    "skillName": "Digital Marketing Strategy",
    "providerName": "Maya Ahmed",
    "providerEmail": "maya@skillswap.com",
    "price": 30,
    "rating": 4.7,
    "slotsAvailable": 5,
    "description": "Learn SEO, social media marketing, and branding for business growth.",
    "image": "https://i.postimg.cc/RFhs06Jk/digital-marketing.png",
    "category": "Marketing"
  },
  {
    "skillId": 7,
    "skillName": "Creative Writing Workshop",
    "providerName": "Tom Richardson",
    "providerEmail": "tom@skillswap.com",
    "price": 15,
    "rating": 4.6,
    "slotsAvailable": 7,
    "description": "Improve storytelling, tone, and flow for fiction and non-fiction writing.",
    "image": "https://i.postimg.cc/zG3kcb5f/creative-writing.png",
    "category": "Writing"
  },
  {
    "skillId": 8,
    "skillName": "Graphic Design with Canva",
    "providerName": "Hannah Khan",
    "providerEmail": "hannah@skillswap.com",
    "price": 12,
    "rating": 4.8,
    "slotsAvailable": 8,
    "description": "Create eye-catching posters, banners, and social media designs using Canva.",
    "image": "https://i.postimg.cc/wBxJpsgb/graphic-design.png",
    "category": "Design"
  },
  {
    "skillId": 9,
    "skillName": "Introduction to Python Programming",
    "providerName": "Rajesh Gupta",
    "providerEmail": "rajesh@skillswap.com",
    "price": 25,
    "rating": 4.9,
    "slotsAvailable": 3,
    "description": "Learn Python from scratch with practical coding challenges.",
    "image": "https://i.postimg.cc/W4Ch8CNR/python-course.png",
    "category": "Technology"
  },
  {
    "skillId": 10,
    "skillName": "Yoga for Beginners",
    "providerName": "Emma Johnson",
    "providerEmail": "emma@skillswap.com",
    "price": 8,
    "rating": 4.5,
    "slotsAvailable": 10,
    "description": "Relax your body and mind with guided yoga sessions for all levels.",
    "image": "https://i.postimg.cc/Zq2HQP7k/yoga-class.png",
    "category": "Health & Fitness"
  },
  {
    "skillId": 11,
    "skillName": "Cooking Basics: Quick & Easy Meals",
    "providerName": "Nora Williams",
    "providerEmail": "nora@skillswap.com",
    "price": 10,
    "rating": 4.6,
    "slotsAvailable": 6,
    "description": "Learn to prepare delicious home-style meals with minimal ingredients.",
    "image": "https://i.postimg.cc/Fs8Cv9s8/cooking-course.png",
    "category": "Culinary"
  },
  {
    "skillId": 12,
    "skillName": "Entrepreneurship Masterclass",
    "providerName": "David Chen",
    "providerEmail": "david@skillswap.com",
    "price": 40,
    "rating": 5.0,
    "slotsAvailable": 3,
    "description": "Turn your ideas into a business with real-world strategies and mentorship.",
    "image": "https://i.postimg.cc/HLnvrS8m/entrepreneurship.png",
    "category": "Business"
  }
]
